flashorm/__init__.py
flashorm/cli.py
flashorm/install.py
flashorm/bin/flash
flashorm-2.2.21.dist-info/licenses/LICENSE
flashorm-2.2.21.dist-info/METADATA
flashorm-2.2.21.dist-info/WHEEL
flashorm-2.2.21.dist-info/entry_points.txt
flashorm-2.2.21.dist-info/top_level.txt
flashorm-2.2.21.dist-info/RECORD
