Metadata-Version: 2.4
Name: flashorm
Version: 2.2.21
Summary: A powerful, database-agnostic ORM with multi-database support and type-safe code generation
Home-page: https://github.com/Lumos-Labs-HQ/flash
Author: Rana718
Author-email: 
License-Expression: MIT
Project-URL: Homepage, https://github.com/Lumos-Labs-HQ/flash
Project-URL: Repository, https://github.com/Lumos-Labs-HQ/flash
Project-URL: Issues, https://github.com/Lumos-Labs-HQ/flash/issues
Keywords: orm,database,migration,postgresql,mysql,sqlite,cli
Classifier: Development Status :: 4 - Beta
Classifier: Intended Audience :: Developers
Classifier: Programming Language :: Python :: 3
Classifier: Programming Language :: Python :: 3.7
Classifier: Programming Language :: Python :: 3.8
Classifier: Programming Language :: Python :: 3.9
Classifier: Programming Language :: Python :: 3.10
Classifier: Programming Language :: Python :: 3.11
Requires-Python: >=3.7
License-File: LICENSE
Dynamic: home-page
Dynamic: license-file
Dynamic: requires-python
